cli.py
template/cookiecutter.json
template/{{cookiecutter.project_slug}}/.dockerignore
template/{{cookiecutter.project_slug}}/Dockerfile
template/{{cookiecutter.project_slug}}/README.md
template/{{cookiecutter.project_slug}}/alembic/env.py
template/{{cookiecutter.project_slug}}/alembic.ini
template/{{cookiecutter.project_slug}}/app/__init__.py
template/{{cookiecutter.project_slug}}/app/api/__init__.py
template/{{cookiecutter.project_slug}}/app/api/public/__init__.py
template/{{cookiecutter.project_slug}}/app/api/public/endpoint1.py
template/{{cookiecutter.project_slug}}/app/api/staff/__init__.py
template/{{cookiecutter.project_slug}}/app/api/staff/auth.py
template/{{cookiecutter.project_slug}}/app/api/staff/rules.py
template/{{cookiecutter.project_slug}}/app/api/staff/user.py
template/{{cookiecutter.project_slug}}/app/core/__init__.py
template/{{cookiecutter.project_slug}}/app/core/config.py
template/{{cookiecutter.project_slug}}/app/core/database.py
template/{{cookiecutter.project_slug}}/app/core/logger.py
template/{{cookiecutter.project_slug}}/app/core/security.py
template/{{cookiecutter.project_slug}}/app/main.py
template/{{cookiecutter.project_slug}}/app/models/__init__.py
template/{{cookiecutter.project_slug}}/app/models/user.py
template/{{cookiecutter.project_slug}}/app/schemas/__init__.py
template/{{cookiecutter.project_slug}}/app/schemas/token.py
template/{{cookiecutter.project_slug}}/app/schemas/user.py
template/{{cookiecutter.project_slug}}/cli.py
template/{{cookiecutter.project_slug}}/docker-compose.yml
template/{{cookiecutter.project_slug}}/frontend/index.html
template/{{cookiecutter.project_slug}}/frontend/package.json
template/{{cookiecutter.project_slug}}/frontend/postcss.config.cjs
template/{{cookiecutter.project_slug}}/frontend/src/App.vue
template/{{cookiecutter.project_slug}}/frontend/src/assets/tailwind.css
template/{{cookiecutter.project_slug}}/frontend/src/layouts/AdminLayout.vue
template/{{cookiecutter.project_slug}}/frontend/src/main.js
fastapi_vue3_admin-0.0.9.dist-info/LICENSE
fastapi_vue3_admin-0.0.9.dist-info/METADATA
fastapi_vue3_admin-0.0.9.dist-info/WHEEL
fastapi_vue3_admin-0.0.9.dist-info/entry_points.txt
fastapi_vue3_admin-0.0.9.dist-info/RECORD
