Metadata-Version: 2.3
Name: fastapi_vue3_admin
Version: 0.0.9
Summary: FastAPI + Vue3 管理後台腳手架
License: MIT
Author: Jeremy.Huang
Author-email: forpythonwork0225@gmail.com
Requires-Python: >=3.10
Classifier: License :: OSI Approved :: MIT License
Classifier: Programming Language :: Python :: 3
Classifier: Programming Language :: Python :: 3.10
Classifier: Programming Language :: Python :: 3.11
Classifier: Programming Language :: Python :: 3.12
Classifier: Programming Language :: Python :: 3.13
Requires-Dist: aiosqlite (>=0.19.0,<1.0.0)
Requires-Dist: alembic (>=1.13.0,<2.0.0)
Requires-Dist: cookiecutter (>=2.3.0,<3.0.0)
Requires-Dist: fastapi (>=0.110.0,<1.0.0)
Requires-Dist: passlib[bcrypt] (>=1.7.4,<2.0.0)
Requires-Dist: psycopg2-binary (>=2.9.9,<3.0.0)
Requires-Dist: pydantic-settings (>=2.2.1,<3.0.0)
Requires-Dist: python-jose[cryptography] (>=3.3.0,<4.0.0)
Requires-Dist: sqlalchemy (>=2.0.0,<3.0.0)
Requires-Dist: typer[all] (>=0.9.0,<1.0.0)
Requires-Dist: uvicorn[standard] (>=0.29.0,<1.0.0)
Project-URL: Homepage, https://github.com/yourusername/fastapi_vue3_admin
